Workbook
Name aporte: PAINEL!$D$22
Name dividendos_mensais: PAINEL!$D$26
Name pat_acumulado: PAINEL!$D$25
Name perfil: PAINEL!$C$36
Name qtd_anos: PAINEL!$D$23
Name rendimento_carteira: PAINEL!$D$18
Name salario: PAINEL!$D$17
Name sugestao_investimento: PAINEL!$D$19
Name taxa_mensal: PAINEL!$D$24

Sheet PAINEL
B16: CONFIGURAÇÕES
B17: Salário | D17: 5000
B18: Rendimento carteira | D18: 0.006
B19: Sugestão de investimento (30%) | D19: =D17*30% -> 1500
B21: INVESTIMENTO MENSAL
B22: Quanto investir por mês ? | D22: 1500
B23: Por quantos anos? | D23: 5
B24: Taxa de rendimento mensal | D24: 0.01079
B25: Patrimônio acumulado | D25: =FV(taxa_mensal,qtd_anos*12,aporte*-1) -> 125665.37
B26: Dividendos mensais | D26: =pat_acumulado*rendimento_carteira -> 753.99223
B28: Cenários | D28: Dividendo
A29: 2 | B29: Quantos em 2 anos? | C29: =FV($D$24,$A29*12,$D$22*-1) -> 40841.441 | D29: =C29*rendimento_carteira -> 245.04865
A30: 5 | B30: Quantos em 5 anos? | C30: =FV($D$24,$A30*12,$D$22*-1) -> 125665.37 | D30: =C30*rendimento_carteira -> 753.99223
A31: 10 | B31: Quantos em 10 anos? | C31: =FV($D$24,$A31*12,$D$22*-1) -> 364926.32 | D31: =C31*rendimento_carteira -> 2189.5579
A32: 20 | B32: Quantos em 20 anos? | C32: =FV($D$24,$A32*12,$D$22*-1) -> 1687797.6 | D32: =C32*rendimento_carteira -> 10126.786
A33: 30 | B33: Quantos em 30 anos? | C33: =FV($D$24,$A33*12,$D$22*-1) -> 6483254.5 | D33: =C33*rendimento_carteira -> 38899.527
B36: PERFIL | C36: Moderado
B37: VALOR A SER IVESTIDO POR MÊS | C37: =aporte -> 1500
B39: TIPO DE FII | C39: Percentual Sugerido | D39: Valores
B40: PAPEL | C40: =VLOOKUP($C$36&"-"&B40,Planilha2!$A:$D,4,FALSE) -> 0.32 | D40: =C40*$C$37 -> 480
B41: TIJOLO | C41: =VLOOKUP($C$36&"-"&B41,Planilha2!$A:$D,4,FALSE) -> 0.35 | D41: =C41*$C$37 -> 525
B42: HÍBRIDO | C42: =VLOOKUP($C$36&"-"&B42,Planilha2!$A:$D,4,FALSE) -> 0.08 | D42: =C42*$C$37 -> 120
B43: FOFs | C43: =VLOOKUP($C$36&"-"&B43,Planilha2!$A:$D,4,FALSE) -> 0.05 | D43: =C43*$C$37 -> 75
B44: DESENVOLVIMENTO | C44: =VLOOKUP($C$36&"-"&B44,Planilha2!$A:$D,4,FALSE) -> 0.1 | D44: =C44*$C$37 -> 150
B45: HOTELARIAS | C45: =VLOOKUP($C$36&"-"&B45,Planilha2!$A:$D,4,FALSE) -> 0.1 | D45: =C45*$C$37 -> 150
D46: =SUM(D40:D45) -> 1500

Sheet Planilha2
A2: CHAVE | B2: PERFIL | C2: TIPO DE FII | D2: %
A3: =B3&"-"&C3 -> Conservador-PAPEL | B3: Conservador | C3: PAPEL | D3: 0.3 | F3: Moderado-TIJOLO | G3: =VLOOKUP(F3,$A:$D,4,FALSE) -> 0.35
A4: =B4&"-"&C4 -> Conservador-TIJOLO | B4: Conservador | C4: TIJOLO | D4: 0.5
A5: =B5&"-"&C5 -> Conservador-HÍBRIDO | B5: Conservador | C5: HÍBRIDO | D5: 0.1
A6: =B6&"-"&C6 -> Conservador-FOFs | B6: Conservador | C6: FOFs | D6: 0.1
A7: =B7&"-"&C7 -> Conservador-DESENVOLVIMENTO | B7: Conservador | C7: DESENVOLVIMENTO | D7: 0
A8: =B8&"-"&C8 -> Conservador-HOTELARIAS | B8: Conservador | C8: HOTELARIAS | D8: 0
A9: =B9&"-"&C9 -> Moderado-PAPEL | B9: Moderado | C9: PAPEL | D9: 0.32
A10: =B10&"-"&C10 -> Moderado-TIJOLO | B10: Moderado | C10: TIJOLO | D10: 0.35
A11: =B11&"-"&C11 -> Moderado-HÍBRIDO | B11: Moderado | C11: HÍBRIDO | D11: 0.08
A12: =B12&"-"&C12 -> Moderado-FOFs | B12: Moderado | C12: FOFs | D12: 0.05
A13: =B13&"-"&C13 -> Moderado-DESENVOLVIMENTO | B13: Moderado | C13: DESENVOLVIMENTO | D13: 0.1
A14: =B14&"-"&C14 -> Moderado-HOTELARIAS | B14: Moderado | C14: HOTELARIAS | D14: 0.1
A15: =B15&"-"&C15 -> Agressivo-PAPEL | B15: Agressivo | C15: PAPEL | D15: 0.5
... A20: =B20&"-"&C20 -> Agressivo-HOTELARIAS | B20: Agressivo | C20: HOTELARIAS | D20: 0.1
